wsrpc/__init__.py
wsrpc/static/q.js
wsrpc/static/q.min.js
wsrpc/static/wsrpc.js
wsrpc/static/wsrpc.min.js
wsrpc/websocket/__init__.py
wsrpc/websocket/common.py
wsrpc/websocket/handler.py
wsrpc/websocket/route.py
wsrpc/websocket/tools.py
wsrpc_tornado-0.5.2.dist-info/DESCRIPTION.rst
wsrpc_tornado-0.5.2.dist-info/METADATA
wsrpc_tornado-0.5.2.dist-info/metadata.json
wsrpc_tornado-0.5.2.dist-info/RECORD
wsrpc_tornado-0.5.2.dist-info/top_level.txt
wsrpc_tornado-0.5.2.dist-info/WHEEL
