Metadata-Version: 2.0
Name: wsrpc-tornado
Version: 0.5.2
Summary: WSRPC WebSocket RPC for tornado
Home-page: http://github.com/mosquito/wsrpc
Author: Dmitry Orlov <me@mosquito.su>
Author-email: me@mosquito.su
License: LGPLv3
Platform: all
Classifier: Environment :: Console
Classifier: Programming Language :: Python
Requires-Dist: tornado (>=4.2)
Requires-Dist: futures
